inotify/__init__.py
inotify/adapters.py
inotify/calls.py
inotify/constants.py
inotify/library.py
inotify/test_support.py
inotify/resources/README.rst
inotify/resources/requirements.txt
inotify-0.2.11.dist-info/licenses/LICENSE
inotify-0.2.11.dist-info/METADATA
inotify-0.2.11.dist-info/WHEEL
inotify-0.2.11.dist-info/top_level.txt
inotify-0.2.11.dist-info/RECORD
