Metadata-Version: 2.4
Name: inotify
Version: 0.2.11
Summary: An adapter to Linux kernel support for inotify directory-watching.
Home-page: https://github.com/dsoprea/PyInotify
Author: Dustin Oprea
Author-email: myselfasunder@gmail.com
License: GPL 2
Keywords: inotify
License-File: LICENSE
Requires-Dist: build
Dynamic: author
Dynamic: author-email
Dynamic: description
Dynamic: home-page
Dynamic: keywords
Dynamic: license
Dynamic: license-file
Dynamic: requires-dist
Dynamic: summary
